LICENSE
README.md
pyproject.toml
tests/__init__.py
tests/test_unstable_populations.py
unstable_populations/__init__.py
unstable_populations/unstable_populations.py
unstable_populations.egg-info/PKG-INFO
unstable_populations.egg-info/SOURCES.txt
unstable_populations.egg-info/dependency_links.txt
unstable_populations.egg-info/requires.txt
unstable_populations.egg-info/top_level.txt