Metadata-Version: 2.1
Name: unstable-populations
Version: 0.6.0
Summary: Package to work with te Unstable Population Indicator
Author: Lisette Sibbald
Author-email: Marcel Haas <datascience@marcelhaas.com>
License: MIT
Project-URL: homepage, https://github.com/harcel/unstable_populations
License-File: LICENSE
Requires-Dist: numpy
Requires-Dist: pandas
